CHANGES.txt
LICENSE.txt
README.txt
setup.py
src/getpaid/__init__.py
src/getpaid.ups.egg-info/PKG-INFO
src/getpaid.ups.egg-info/SOURCES.txt
src/getpaid.ups.egg-info/dependency_links.txt
src/getpaid.ups.egg-info/namespace_packages.txt
src/getpaid.ups.egg-info/not-zip-safe
src/getpaid.ups.egg-info/requires.txt
src/getpaid.ups.egg-info/top_level.txt
src/getpaid/ups/__init__.py
src/getpaid/ups/configure.zcml
src/getpaid/ups/i18n.sh
src/getpaid/ups/interfaces.py
src/getpaid/ups/plugin.py
src/getpaid/ups/rates.py
src/getpaid/ups/readme.txt
src/getpaid/ups/tests.py
src/getpaid/ups/browser/__init__.py
src/getpaid/ups/browser/admin.py
src/getpaid/ups/browser/configure.zcml
src/getpaid/ups/browser/templates/orders-export-worldship-csv.pt
src/getpaid/ups/doc/RSS-WW-XML.pdf
src/getpaid/ups/locales/getpaid.ups.pot
src/getpaid/ups/locales/manual.pot