Metadata-Version: 1.0
Name: getpaid.ups
Version: 0.3
Summary: Get paid UPS functionality
Home-page: UNKNOWN
Author: getpaid community
Author-email: getpaid-dev@googlegroups.com
License: UNKNOWN
Platform: UNKNOWN
Classifier: Framework :: Plone
Classifier: Programming Language :: Python
Classifier: Framework :: Zope3
Classifier: Intended Audience :: Developers
Classifier: License :: OSI Approved :: Zope Public License
Classifier: Operating System :: OS Independent
Classifier: Topic :: Office/Business :: Financial
Classifier: Topic :: Software Development :: Libraries
